[{"person":"soandso","msgin":"funcionas a cualquier hora?","msgout":"Unknown","date":"2017-04-24T19:35:48.760Z","_id":"fd3638fea62a40b6a1650598c964de0f"},{"person":"soandso","msgin":"como pago un nomica","msgout":"Unknown","date":"2017-04-24T19:37:26.244Z","_id":"dcefa9984bb3442a8dca39b0f56dfdd4"},{"person":"soandso","msgin":"cual es la clave?","msgout":"Unknown","date":"2017-04-24T19:37:45.351Z","_id":"1641853391a24a3d91b52d8c9c7163f2"},{"person":"soandso","msgin":"que clave necesito para pagar","msgout":"Unknown","date":"2017-04-24T19:37:53.982Z","_id":"bbd9c8ec14f84d66ba3ed2e53ea8086b"},{"person":"soandso","msgin":"que es PNOL","msgout":"Unknown","date":"2017-04-24T19:38:27.441Z","_id":"bfc041a3f09b476189dca30fe4b2a29a"},{"person":"soandso","msgin":"cuanto cuesta","msgout":"Unknown","date":"2017-04-25T13:20:29.368Z","_id":"e4131eb00c53420db05a3fdfa2f3241f"},{"person":"soandso","msgin":"Tiene costo?","msgout":"Unknown","date":"2017-04-25T13:22:49.155Z","_id":"c8c7c9506d6f4bfcb85f57d23926461b"},{"person":"soandso","msgin":"es gratis?","msgout":"Unknown","date":"2017-04-25T13:22:59.664Z","_id":"69c7599c02774717b1cd4434c1e03cc9"},{"person":"soandso","msgin":"tiene un minimo de personas?","msgout":"Unknown","date":"2017-04-25T13:48:47.996Z","_id":"877de8773a9f4d609cfa26c92ab24df0"},{"person":"soandso","msgin":"tiene minimo de personas a transferir?","msgout":"Unknown","date":"2017-04-25T13:49:06.886Z","_id":"aa9ba28902de4a929350ad4f670b745d"},{"person":"soandso","msgin":"hay limite de trabajadores para transferencias?","msgout":"Unknown","date":"2017-04-25T14:33:17.617Z","_id":"3846073ec3854c14aa636c18fc74bea1"},{"person":"soandso","msgin":"hay limite de monto?","msgout":"Unknown","date":"2017-04-25T14:33:30.787Z","_id":"4e110766288e4cc6b7bae950101d6c32"},{"person":"soandso","msgin":"que es una nomina","msgout":"Unknown","date":"2017-04-25T15:44:47.167Z","_id":"2167e854d63a4a89b847880efbf7cd44"},{"person":"soandso","msgin":"nominas","msgout":"Unknown","date":"2017-04-25T15:52:41.067Z","_id":"d5f6a66dfa294d8bb21c416e39d55ac0"},{"person":"soandso","msgin":"necesito informació sobre nomina","msgout":"Unknown","date":"2017-04-25T15:52:55.340Z","_id":"58a56a09593c4c73b89627288ae2cd31"},{"person":"soandso","msgin":"hola estoy tratando de sacar un certificado de transferencia pero no sale","msgout":"Unknown","date":"2017-04-25T16:07:53.377Z","_id":"193566c1bef645a380935d9e7af0b902"},{"person":"soandso","msgin":"No sé. Eres una persona o un bot?","msgout":"Unknown","date":"2017-04-25T18:44:00.731Z","_id":"7b5948b4ad4e4bd5badce6414763946a"},{"person":"soandso","msgin":"No creo que me puedas ayudar ERR","msgout":"Unknown","date":"2017-04-25T18:45:51.902Z","_id":"dac0e44c870e40009d040dabfde02857"},{"person":"soandso","msgin":"Who are you?","msgout":"Unknown","date":"2017-04-25T18:49:32.830Z","_id":"43237c4612074698852d4765f54ac3be"},{"person":"soandso","msgin":"Hellow","msgout":"Unknown","date":"2017-04-25T18:49:57.112Z","_id":"c1b3d940ad7d4448bba687144a485c1c"},{"person":"soandso","msgin":"H","msgout":"Unknown","date":"2017-04-25T18:50:09.269Z","_id":"7fdc8ec58e1a49c1ab481b3b35761449"},{"person":"soandso","msgin":"H i","msgout":"Unknown","date":"2017-04-25T18:50:20.204Z","_id":"99c89c93765d49219181e9d83e2d7792"},{"person":"soandso","msgin":"Good morning","msgout":"Unknown","date":"2017-04-25T18:50:46.163Z","_id":"8e0cc25aab1a4e42a9ade0e55ee3068b"},{"person":"soandso","msgin":"Cómo sé cual es el error?","msgout":"Unknown","date":"2017-04-27T20:27:47.940Z","_id":"3c1bf2678f07492987b3b1f03a0f9a05"},{"person":"soandso","msgin":"    a que se refiere a nomina diferida?","msgout":"Unknown","date":"2017-04-28T18:42:15.642Z","_id":"b51844f8991f46c1a898cc2911c9393c"},{"person":"soandso","msgin":"que es nómina diferida¿","msgout":"Unknown","date":"2017-04-28T18:47:17.646Z","_id":"42464c542bfd44f9b52b295fe3b8d637"},{"person":"soandso","msgin":"nomina diferida?","msgout":"Unknown","date":"2017-04-28T18:47:24.564Z","_id":"0325ed78b0a94e0c937d68fe3151e2a2"},{"person":"soandso","msgin":"cual es el máximo de destinatarios de una nómina?","msgout":"Unknown","date":"2017-04-28T18:57:58.606Z","_id":"d57b7da76c6d4ff79f70b0c682ed6c13"},{"person":"soandso","msgin":"    A QUE SE DEBEN LOS ERRORES DE CUENTA NO ALFANUMERICA","msgout":"Unknown","date":"2017-04-28T19:20:22.616Z","_id":"08fdfc8adac44c24b2faad55ab76bf37"}]